kapital_game_sdk/__init__.py
kapital_game_sdk/errors.py
kapital_game_sdk/game_base.py
kapital_game_sdk/game_config.py
kapital_game_sdk/models.py
kapital_game_sdk-0.1.0.dist-info/WHEEL
kapital_game_sdk-0.1.0.dist-info/METADATA
kapital_game_sdk-0.1.0.dist-info/RECORD
