Metadata-Version: 2.1
Name: kapital-game-sdk
Version: 0.1.0
Summary: 
Author: Playground Labs
Requires-Python: >=3.9,<4.0
Classifier: Programming Language :: Python :: 3
Classifier: Programming Language :: Python :: 3.9
Classifier: Programming Language :: Python :: 3.10
Requires-Dist: PyYAML (>=6.0,<7.0)
Requires-Dist: requests (>=2.28.1,<3.0.0)
Requires-Dist: types-PyYAML (>=6.0.11,<7.0.0)
